restcountries/__init__.py
restcountries/base.py
restcountries/tests/__init__.py
restcountries/tests/conftest.py
restcountries/tests/countries_data.py
restcountries/tests/test_base.py
python_restcountries-2.0.0.dist-info/METADATA
python_restcountries-2.0.0.dist-info/WHEEL
python_restcountries-2.0.0.dist-info/top_level.txt
python_restcountries-2.0.0.dist-info/RECORD
