Metadata-Version: 2.1
Name: python-restcountries
Version: 2.0.0
Summary: Python API Wrapper for restcountries.com
Home-page: https://github.com/SteinRobert/python-restcountries
Author: Robert Stein
Author-email: robert@blueshoe.de
License: Unlicense
Download-URL: https://github.com/SteinRobert/python-restcountries/tarball/2.0.0
Keywords: api,wrapper,country,countries
Platform: UNKNOWN
Classifier: Programming Language :: Python :: 3 :: Only
